Metadata-Version: 2.1
Name: knackpy-dev
Version: 1.1.1
Summary: A Python API client for interacting with Knack applications.
Home-page: http://github.com/cityofaustin/knackpy
Author: John Clary
Author-email: john.clary@austintexas.gov
License: Public Domain
Keywords: knack api api-client integration python
Platform: UNKNOWN
Classifier: Development Status :: 4 - Beta
Classifier: Intended Audience :: Developers
Classifier: License :: Public Domain
Classifier: Programming Language :: Python :: 3
License-File: LICENSE.md
Requires-Dist: pytz
Requires-Dist: requests
